{
	"parent": "simplehats:item/hatparent",
	"texture_size": [32, 32],
	"textures": {
		"0": "simplehats:item/hats/rabbitonhead"
	},
	"elements": [
		{
			"from": [6, 14, 5],
			"to": [10, 18, 10],
			"faces": {
				"north": {"uv": [0.016, 4.016, 1.984, 5.984], "texture": "#0"},
				"east": {"uv": [0.016, 0.016, 2.484, 1.984], "texture": "#0"},
				"south": {"uv": [4.516, 0.016, 6.484, 1.984], "texture": "#0"},
				"west": {"uv": [0.016, 2.016, 2.484, 3.984], "texture": "#0"},
				"up": {"uv": [4.484, 2.484, 2.516, 0.016], "texture": "#0"},
				"down": {"uv": [4.484, 2.516, 2.516, 4.984], "texture": "#0"}
			}
		},
		{
			"from": [10, 14, 6.5],
			"to": [11, 17, 9.5],
			"faces": {
				"north": {"uv": [4.016, 8.016, 4.484, 9.484], "texture": "#0"},
				"east": {"uv": [6.516, 3.016, 7.984, 4.484], "texture": "#0"},
				"south": {"uv": [4.516, 8.016, 4.984, 9.484], "texture": "#0"},
				"west": {"uv": [6.516, 4.516, 7.984, 5.984], "texture": "#0"},
				"up": {"uv": [8.484, 5.984, 8.016, 4.516], "texture": "#0"},
				"down": {"uv": [5.484, 8.016, 5.016, 9.484], "texture": "#0"}
			}
		},
		{
			"from": [5, 14, 6.5],
			"to": [6, 17, 9.5],
			"faces": {
				"north": {"uv": [1.016, 8.016, 1.484, 9.484], "texture": "#0"},
				"east": {"uv": [6.516, 0.016, 7.984, 1.484], "texture": "#0"},
				"south": {"uv": [1.516, 8.016, 1.984, 9.484], "texture": "#0"},
				"west": {"uv": [6.516, 1.516, 7.984, 2.984], "texture": "#0"},
				"up": {"uv": [8.484, 2.984, 8.016, 1.516], "texture": "#0"},
				"down": {"uv": [8.484, 3.016, 8.016, 4.484], "texture": "#0"}
			}
		},
		{
			"from": [5, 14, 5.5],
			"to": [6, 16, 6.5],
			"faces": {
				"north": {"uv": [2.016, 4.016, 2.484, 4.984], "texture": "#0"},
				"east": {"uv": [4.016, 5.016, 4.484, 5.984], "texture": "#0"},
				"south": {"uv": [7.016, 8.016, 7.484, 8.984], "texture": "#0"},
				"west": {"uv": [7.516, 8.016, 7.984, 8.984], "texture": "#0"},
				"up": {"uv": [9.484, 1.984, 9.016, 1.516], "texture": "#0"},
				"down": {"uv": [9.484, 2.016, 9.016, 2.484], "texture": "#0"}
			}
		},
		{
			"from": [10, 14, 5.5],
			"to": [11, 16, 6.5],
			"faces": {
				"north": {"uv": [8.016, 7.516, 8.484, 8.484], "texture": "#0"},
				"east": {"uv": [8.516, 1.516, 8.984, 2.484], "texture": "#0"},
				"south": {"uv": [2.016, 8.516, 2.484, 9.484], "texture": "#0"},
				"west": {"uv": [2.516, 8.516, 2.984, 9.484], "texture": "#0"},
				"up": {"uv": [9.484, 2.984, 9.016, 2.516], "texture": "#0"},
				"down": {"uv": [9.484, 3.016, 9.016, 3.484], "texture": "#0"}
			}
		},
		{
			"from": [6, 14, 4],
			"to": [7, 16, 5],
			"faces": {
				"north": {"uv": [8.516, 2.516, 8.984, 3.484], "texture": "#0"},
				"east": {"uv": [3.016, 8.516, 3.484, 9.484], "texture": "#0"},
				"south": {"uv": [3.516, 8.516, 3.984, 9.484], "texture": "#0"},
				"west": {"uv": [8.516, 3.516, 8.984, 4.484], "texture": "#0"},
				"up": {"uv": [9.484, 3.984, 9.016, 3.516], "texture": "#0"},
				"down": {"uv": [9.484, 4.016, 9.016, 4.484], "texture": "#0"}
			}
		},
		{
			"from": [9, 14, 4],
			"to": [10, 16, 5],
			"faces": {
				"north": {"uv": [8.516, 4.516, 8.984, 5.484], "texture": "#0"},
				"east": {"uv": [8.516, 5.516, 8.984, 6.484], "texture": "#0"},
				"south": {"uv": [8.516, 6.516, 8.984, 7.484], "texture": "#0"},
				"west": {"uv": [8.516, 7.516, 8.984, 8.484], "texture": "#0"},
				"up": {"uv": [9.484, 4.984, 9.016, 4.516], "texture": "#0"},
				"down": {"uv": [9.484, 5.016, 9.016, 5.484], "texture": "#0"}
			}
		},
		{
			"from": [6, 18, 4.5],
			"to": [10, 22, 8.5],
			"faces": {
				"north": {"uv": [4.516, 2.016, 6.484, 3.984], "texture": "#0"},
				"east": {"uv": [4.516, 4.016, 6.484, 5.984], "texture": "#0"},
				"south": {"uv": [2.016, 5.016, 3.984, 6.984], "texture": "#0"},
				"west": {"uv": [0.016, 6.016, 1.984, 7.984], "texture": "#0"},
				"up": {"uv": [5.984, 7.984, 4.016, 6.016], "texture": "#0"},
				"down": {"uv": [7.984, 6.016, 6.016, 7.984], "texture": "#0"}
			}
		},
		{
			"from": [8.5, 22, 6.5],
			"to": [10.5, 25, 7.5],
			"faces": {
				"north": {"uv": [2.016, 7.016, 2.984, 8.484], "texture": "#0"},
				"east": {"uv": [5.516, 8.016, 5.984, 9.484], "texture": "#0"},
				"south": {"uv": [3.016, 7.016, 3.984, 8.484], "texture": "#0"},
				"west": {"uv": [6.016, 8.016, 6.484, 9.484], "texture": "#0"},
				"up": {"uv": [8.984, 8.984, 8.016, 8.516], "texture": "#0"},
				"down": {"uv": [9.984, 0.016, 9.016, 0.484], "texture": "#0"}
			}
		},
		{
			"from": [5.5, 22, 6.5],
			"to": [7.5, 25, 7.5],
			"faces": {
				"north": {"uv": [0.016, 8.016, 0.984, 9.484], "texture": "#0"},
				"east": {"uv": [8.016, 6.016, 8.484, 7.484], "texture": "#0"},
				"south": {"uv": [8.016, 0.016, 8.984, 1.484], "texture": "#0"},
				"west": {"uv": [6.516, 8.016, 6.984, 9.484], "texture": "#0"},
				"up": {"uv": [9.984, 0.984, 9.016, 0.516], "texture": "#0"},
				"down": {"uv": [9.984, 1.016, 9.016, 1.484], "texture": "#0"}
			}
		},
		{
			"from": [7, 15, 10],
			"to": [9, 17, 12],
			"faces": {
				"north": {"uv": [9.016, 3.516, 9.984, 4.484], "texture": "#0"},
				"east": {"uv": [9.016, 4.516, 9.984, 5.484], "texture": "#0"},
				"south": {"uv": [9.016, 5.516, 9.984, 6.484], "texture": "#0"},
				"west": {"uv": [9.016, 6.516, 9.984, 7.484], "texture": "#0"},
				"up": {"uv": [9.016, 7.516, 9.984, 8.484], "texture": "#0"},
				"down": {"uv": [9.016, 8.516, 9.984, 9.484], "texture": "#0"}
			}
		}
	],
	"display": {
		"thirdperson_righthand": {
			"translation": [0, -5.5, 0],
			"scale": [0.55, 0.55, 0.55]
		},
		"thirdperson_lefthand": {
			"translation": [0, -5.5, 0],
			"scale": [0.55, 0.55, 0.55]
		},
		"firstperson_righthand": {
			"rotation": [0, 135, 0],
			"translation": [2, -3.5, 0],
			"scale": [0.75, 0.75, 0.75]
		},
		"firstperson_lefthand": {
			"rotation": [0, 135, 0],
			"translation": [2, -3.5, 0],
			"scale": [0.75, 0.75, 0.75]
		},
		"ground": {
			"translation": [0, -11.5, 0]
		},
		"gui": {
			"rotation": [35, -135, 0],
			"translation": [0, -8.5, 0]
		},
		"fixed": {
			"translation": [0, -10.5, 0],
			"scale": [1, 1, 0.04]
		}
	}
}