{
	"parent": "simplehats:item/hatparent",
	"texture_size": [32, 32],
	"textures": {
		"0": "simplehats:item/hats/triangleshades"
	},
	"elements": [
		{
			"from": [8.41267, 5, 0.5],
			"to": [17.41267, 11, 0.55],
			"rotation": {"angle": 22.5, "axis": "z", "origin": [8.01267, 7, 0.5]},
			"faces": {
				"north": {"uv": [0, 0, 4.5, 3], "texture": "#0"},
				"east": {"uv": [0, 7, 0.5, 10], "texture": "#0"},
				"south": {"uv": [0, 0, 4.5, 3], "texture": "#0"},
				"west": {"uv": [0.5, 7, 1, 10], "texture": "#0"},
				"up": {"uv": [4.5, 6.5, 0, 6], "texture": "#0"},
				"down": {"uv": [9, 6, 4.5, 6.5], "texture": "#0"}
			}
		},
		{
			"from": [17.38767, 5, 0.5],
			"to": [17.41267, 11, 7],
			"rotation": {"angle": 22.5, "axis": "z", "origin": [8.01267, 7, 0.5]},
			"faces": {
				"north": {"uv": [2.5, 6.5, 7, 9.5], "texture": "#0"},
				"east": {"uv": [0, 7, 0.5, 10], "texture": "#0"},
				"south": {"uv": [10.5, 7, 11, 10], "texture": "#0"},
				"west": {"uv": [0, 7, 0.5, 10], "texture": "#0"},
				"up": {"uv": [4.5, 6.5, 0, 6], "texture": "#0"},
				"down": {"uv": [9, 6, 4.5, 6.5], "texture": "#0"}
			}
		},
		{
			"from": [-1.4, 5, 0.5],
			"to": [7.6, 11, 0.525],
			"rotation": {"angle": -22.5, "axis": "z", "origin": [8, 7, 0.5]},
			"faces": {
				"north": {"uv": [4.5, 0, 9, 3], "texture": "#0"},
				"east": {"uv": [1, 7, 1.5, 10], "texture": "#0"},
				"south": {"uv": [4.5, 0, 9, 3], "texture": "#0"},
				"west": {"uv": [1.5, 7, 2, 10], "texture": "#0"},
				"up": {"uv": [4.5, 7, 0, 6.5], "texture": "#0"},
				"down": {"uv": [9, 6.5, 4.5, 7], "texture": "#0"}
			}
		},
		{
			"from": [-1.4, 5, 0.5],
			"to": [-1.375, 11, 7],
			"rotation": {"angle": -22.5, "axis": "z", "origin": [8, 7, 0.5]},
			"faces": {
				"north": {"uv": [2.5, 7.5, 7, 10.5], "texture": "#0"},
				"east": {"uv": [1.5, 7, 2, 10], "texture": "#0"},
				"south": {"uv": [4.5, 3, 9, 6], "texture": "#0"},
				"west": {"uv": [1.5, 7, 2, 10], "texture": "#0"},
				"up": {"uv": [4.5, 7, 0, 6.5], "texture": "#0"},
				"down": {"uv": [9, 6.5, 4.5, 7], "texture": "#0"}
			}
		}
	],
	"display": {
		"head": {
			"translation": [0, -1.25, 0]
		}
	}
}